{
  "headers": [
    "",
    "Name",
    "G",
    "Sacks",
    "Sack Yards",
    "Sacks/G"
  ],
  "rows": [
    {
      "": "1",
      "Name": "Wisconsin",
      "G": "12",
      "Sacks": "13.0",
      "Sack Yards": "82",
      "Sacks/G": "1.08"
    },
    {
      "": "2",
      "Name": "USC",
      "G": "13",
      "Sacks": "15.0",
      "Sack Yards": "105",
      "Sacks/G": "1.15"
    },
    {
      "": "3",
      "Name": "Ohio State",
      "G": "16",
      "Sacks": "16.0",
      "Sack Yards": "96",
      "Sacks/G": "1.00"
    },
    {
      "": "4",
      "Name": "Michigan",
      "G": "13",
      "Sacks": "17.0",
      "Sack Yards": "108",
      "Sacks/G": "1.31"
    },
    {
      "": "4",
      "Name": "Iowa",
      "G": "13",
      "Sacks": "17.0",
      "Sack Yards": "119",
      "Sacks/G": "1.31"
    },
    {
      "": "6",
      "Name": "Penn State",
      "G": "16",
      "Sacks": "20.0",
      "Sack Yards": "142",
      "Sacks/G": "1.25"
    },
    {
      "": "7",
      "Name": "Rutgers",
      "G": "13",
      "Sacks": "21.0",
      "Sack Yards": "124",
      "Sacks/G": "1.62"
    },
    {
      "": "7",
      "Name": "Indiana",
      "G": "13",
      "Sacks": "21.0",
      "Sack Yards": "159",
      "Sacks/G": "1.62"
    },
    {
      "": "7",
      "Name": "Oregon",
      "G": "14",
      "Sacks": "21.0",
      "Sack Yards": "162",
      "Sacks/G": "1.50"
    },
    {
      "": "10",
      "Name": "Northwestern",
      "G": "12",
      "Sacks": "24.0",
      "Sack Yards": "173",
      "Sacks/G": "2.00"
    },
    {
      "": "11",
      "Name": "Minnesota",
      "G": "13",
      "Sacks": "26.0",
      "Sack Yards": "174",
      "Sacks/G": "2.00"
    },
    {
      "": "11",
      "Name": "Maryland",
      "G": "12",
      "Sacks": "26.0",
      "Sack Yards": "200",
      "Sacks/G": "2.17"
    },
    {
      "": "13",
      "Name": "Nebraska",
      "G": "13",
      "Sacks": "28.0",
      "Sack Yards": "187",
      "Sacks/G": "2.15"
    },
    {
      "": "14",
      "Name": "Illinois",
      "G": "13",
      "Sacks": "32.0",
      "Sack Yards": "204",
      "Sacks/G": "2.46"
    },
    {
      "": "14",
      "Name": "Purdue",
      "G": "12",
      "Sacks": "32.0",
      "Sack Yards": "227",
      "Sacks/G": "2.67"
    },
    {
      "": "16",
      "Name": "UCLA",
      "G": "12",
      "Sacks": "34.0",
      "Sack Yards": "234",
      "Sacks/G": "2.83"
    },
    {
      "": "17",
      "Name": "Michigan State",
      "G": "12",
      "Sacks": "36.0",
      "Sack Yards": "237",
      "Sacks/G": "3.00"
    },
    {
      "": "18",
      "Name": "Washington",
      "G": "13",
      "Sacks": "39.0",
      "Sack Yards": "240",
      "Sacks/G": "3.00"
    }
  ],
  "fetched_at": "2026-02-16T22:34:30.351550Z"
}