{
  "headers": [
    "",
    "Name",
    "G",
    "Total Time",
    "Time/G"
  ],
  "rows": [
    {
      "": "1",
      "Name": "Wisconsin",
      "G": "3",
      "Total Time": "102:03",
      "Time/G": "34:01.00"
    },
    {
      "": "2",
      "Name": "Michigan",
      "G": "4",
      "Total Time": "135:16",
      "Time/G": "33:49.00"
    },
    {
      "": "3",
      "Name": "Minnesota",
      "G": "4",
      "Total Time": "134:38",
      "Time/G": "33:39.50"
    },
    {
      "": "4",
      "Name": "Rutgers",
      "G": "4",
      "Total Time": "134:07",
      "Time/G": "33:31.75"
    },
    {
      "": "5",
      "Name": "Maryland",
      "G": "3",
      "Total Time": "97:40",
      "Time/G": "32:33.33"
    },
    {
      "": "6",
      "Name": "Iowa",
      "G": "4",
      "Total Time": "129:27",
      "Time/G": "32:21.75"
    },
    {
      "": "7",
      "Name": "Michigan State",
      "G": "3",
      "Total Time": "96:48",
      "Time/G": "32:16.00"
    },
    {
      "": "8",
      "Name": "Oregon",
      "G": "3",
      "Total Time": "95:46",
      "Time/G": "31:55.33"
    },
    {
      "": "9",
      "Name": "Nebraska",
      "G": "4",
      "Total Time": "127:02",
      "Time/G": "31:45.50"
    },
    {
      "": "10",
      "Name": "Northwestern",
      "G": "3",
      "Total Time": "94:53",
      "Time/G": "31:37.67"
    },
    {
      "": "11",
      "Name": "Illinois",
      "G": "4",
      "Total Time": "126:20",
      "Time/G": "31:35.00"
    },
    {
      "": "12",
      "Name": "Washington",
      "G": "4",
      "Total Time": "122:17",
      "Time/G": "30:34.25"
    },
    {
      "": "13",
      "Name": "Indiana",
      "G": "4",
      "Total Time": "121:47",
      "Time/G": "30:26.75"
    },
    {
      "": "14",
      "Name": "UCLA",
      "G": "3",
      "Total Time": "91:12",
      "Time/G": "30:24.00"
    },
    {
      "": "15",
      "Name": "Penn State",
      "G": "6",
      "Total Time": "181:11",
      "Time/G": "30:11.83"
    },
    {
      "": "16",
      "Name": "Ohio State",
      "G": "6",
      "Total Time": "181:10",
      "Time/G": "30:11.67"
    },
    {
      "": "17",
      "Name": "USC",
      "G": "4",
      "Total Time": "118:15",
      "Time/G": "29:33.75"
    },
    {
      "": "18",
      "Name": "Purdue",
      "G": "3",
      "Total Time": "73:33",
      "Time/G": "24:31.00"
    }
  ],
  "fetched_at": "2026-02-16T22:35:06.859250Z"
}